tox_workdir/__init__.py
tox_workdir/py.typed
tox_workdir-0.1.0.dist-info/LICENSE.txt
tox_workdir-0.1.0.dist-info/METADATA
tox_workdir-0.1.0.dist-info/WHEEL
tox_workdir-0.1.0.dist-info/entry_points.txt
tox_workdir-0.1.0.dist-info/RECORD
