Metadata-Version: 2.1
Name: tox-workdir
Version: 0.1.0
Summary: Put tox work directories in a cache directory by default
Home-page: https://github.com/kurtmckee/tox-workdir
License: MIT
Keywords: tox,plugin
Author: Kurt McKee
Author-email: contactme@kurtmckee.org
Requires-Python: >=3.9
Classifier: Development Status :: 4 - Beta
Classifier: Framework :: tox
Classifier: Intended Audience :: Developers
Classifier: License :: OSI Approved :: MIT License
Classifier: Programming Language :: Python :: 3
Classifier: Programming Language :: Python :: 3.9
Classifier: Programming Language :: Python :: 3.10
Classifier: Programming Language :: Python :: 3.11
Classifier: Programming Language :: Python :: 3.12
Classifier: Programming Language :: Python :: 3.13
Requires-Dist: platformdirs (>=4,<5)
Requires-Dist: tox (>=4,<5)
Project-URL: Repository, https://github.com/kurtmckee/tox-workdir
